umndet/__init__.py
umndet/plotting.py
umndet-0.2.1.dist-info/LICENSE
umndet-0.2.1.dist-info/METADATA
umndet-0.2.1.dist-info/WHEEL
umndet-0.2.1.dist-info/entry_points.txt
umndet-0.2.1.dist-info/top_level.txt
umndet-0.2.1.dist-info/RECORD
